analys/__init__.py
analys-0.1.0.dist-info/METADATA
analys-0.1.0.dist-info/WHEEL
analys-0.1.0.dist-info/top_level.txt
analys-0.1.0.dist-info/RECORD
