Metadata-Version: 2.4
Name: analys
Version: 0.1.0
Summary: To perform practical of Analysis of Varience.
Author: Aryan Bhagwat
Author-email: legendasur531@gmail.com
Classifier: Programming Language :: Python :: 3
Classifier: Operating System :: OS Independent
Requires-Python: >=3.6
Dynamic: author
Dynamic: author-email
Dynamic: classifier
Dynamic: requires-python
Dynamic: summary
